event2vec/__init__.py
event2vec/concept_proximity.py
event2vec/config.py
event2vec/cooccurrence_matrix_pandas.py
event2vec/cooccurrence_matrix_polars.py
event2vec/cooccurrence_matrix_spark.py
event2vec/datasets.py
event2vec/event_transformer.py
event2vec/nomenclatures.py
event2vec/svd_ppmi.py
event2vec/utils.py
event2vec-0.0.46.dist-info/LICENSE
event2vec-0.0.46.dist-info/METADATA
event2vec-0.0.46.dist-info/WHEEL
event2vec-0.0.46.dist-info/entry_points.txt
event2vec-0.0.46.dist-info/RECORD
